t_val/__init__.py
t_val/t_val.py
t_val-0.0.3.dist-info/METADATA
t_val-0.0.3.dist-info/WHEEL
t_val-0.0.3.dist-info/top_level.txt
t_val-0.0.3.dist-info/RECORD
