Metadata-Version: 2.1
Name: t-val
Version: 0.0.3
Summary: A Python module for Terraform validation
Home-page: UNKNOWN
Author: M. Vidyaa Shankar
License: UNKNOWN
Platform: UNKNOWN
